google_datacatalog_greenplum_connector-0.9.0-py3.8-nspkg.pth
google/datacatalog_connectors/greenplum/__init__.py
google/datacatalog_connectors/greenplum/datacatalog_cli.py
google_datacatalog_greenplum_connector-0.9.0.dist-info/METADATA
google_datacatalog_greenplum_connector-0.9.0.dist-info/WHEEL
google_datacatalog_greenplum_connector-0.9.0.dist-info/entry_points.txt
google_datacatalog_greenplum_connector-0.9.0.dist-info/namespace_packages.txt
google_datacatalog_greenplum_connector-0.9.0.dist-info/top_level.txt
google_datacatalog_greenplum_connector-0.9.0.dist-info/RECORD
